hocus_pocus/__init__.py
hocus_pocus/py.py
hocus_pocus/tex.py
hocus_pocus/util.py
hocus_pocus-0.1.0.dist-info/WHEEL
hocus_pocus-0.1.0.dist-info/METADATA
hocus_pocus-0.1.0.dist-info/RECORD
