Metadata-Version: 2.1
Name: hocus-pocus
Version: 0.1.0
Summary: 
Home-page: https://github.com/Ohjeah/invocations
License: MIT
Author: Markus Quade
Author-email: info@markusqua.de
Requires-Python: >=3.6,<4.0
Classifier: License :: OSI Approved :: MIT License
Classifier: Programming Language :: Python :: 3
Classifier: Programming Language :: Python :: 3.6
Classifier: Programming Language :: Python :: 3.7
Requires-Dist: invoke
Project-URL: Repository, https://github.com/Ohjeah/invocations
